odoo/addons/ai_oca_bridge_extra_parameters/README.rst
odoo/addons/ai_oca_bridge_extra_parameters/__init__.py
odoo/addons/ai_oca_bridge_extra_parameters/__manifest__.py
odoo/addons/ai_oca_bridge_extra_parameters/i18n/ai_oca_bridge_extra_parameters.pot
odoo/addons/ai_oca_bridge_extra_parameters/i18n/it.po
odoo/addons/ai_oca_bridge_extra_parameters/models/__init__.py
odoo/addons/ai_oca_bridge_extra_parameters/models/ai_bridge.py
odoo/addons/ai_oca_bridge_extra_parameters/models/ai_extra_parameter.py
odoo/addons/ai_oca_bridge_extra_parameters/readme/CONFIGURE.md
odoo/addons/ai_oca_bridge_extra_parameters/readme/CONTRIBUTORS.md
odoo/addons/ai_oca_bridge_extra_parameters/readme/DESCRIPTION.md
odoo/addons/ai_oca_bridge_extra_parameters/readme/USAGE.md
odoo/addons/ai_oca_bridge_extra_parameters/security/ir.model.access.csv
odoo/addons/ai_oca_bridge_extra_parameters/static/description/icon.png
odoo/addons/ai_oca_bridge_extra_parameters/static/description/index.html
odoo/addons/ai_oca_bridge_extra_parameters/tests/__init__.py
odoo/addons/ai_oca_bridge_extra_parameters/tests/test_ai_extra_parameter.py
odoo/addons/ai_oca_bridge_extra_parameters/views/ai_bridge.xml
odoo/addons/ai_oca_bridge_extra_parameters/views/ai_extra_parameter.xml
odoo/addons/ai_oca_bridge_extra_parameters/views/menu.xml
odoo_addon_ai_oca_bridge_extra_parameters-18.0.1.0.0.3.dist-info/METADATA
odoo_addon_ai_oca_bridge_extra_parameters-18.0.1.0.0.3.dist-info/WHEEL
odoo_addon_ai_oca_bridge_extra_parameters-18.0.1.0.0.3.dist-info/top_level.txt
odoo_addon_ai_oca_bridge_extra_parameters-18.0.1.0.0.3.dist-info/RECORD
