Metadata-Version: 2.1
Name: odoo-addon-ai_oca_bridge_extra_parameters
Version: 18.0.1.0.0.3
Requires-Python: >=3.10
Requires-Dist: odoo-addon-ai_oca_bridge==18.0.*
Requires-Dist: odoo==18.0.*
Summary: Adds extra parameters to the AI OCA Bridge payload.
Home-page: https://github.com/OCA/ai
License: AGPL-3
Author: Binhex,Odoo Community Association (OCA)
Author-email: support@odoo-community.org
Classifier: Programming Language :: Python
Classifier: Framework :: Odoo
Classifier: Framework :: Odoo :: 18.0
Classifier: License :: OSI Approved :: GNU Affero General Public License v3
Classifier: Development Status :: 4 - Beta
